babelpy
