Metadata-Version: 1.1
Name: BabelPy
Version: 1.0.1
Summary: BabelFy API Client
Home-page: https://github.com/fbngrm/babelpy
Author: Fabian Grimme
Author-email: fbngrm@googlemail.com
License: GPL
Keywords: nlp computational_linguistics entities wikipedia dbpedia linguistics
Platform: UNKNOWN
Classifier: Development Status :: 5 - Production/Stable
Classifier: Topic :: Text Processing :: Linguistic
Classifier: Programming Language :: Python :: 2.7
Classifier: Programming Language :: Python :: 3
Classifier: Operating System :: POSIX
Classifier: Intended Audience :: Developers
Classifier: Intended Audience :: Science/Research
Classifier: License :: OSI Approved :: GNU General Public License v3 (GPLv3)
